pytest_llm_agent/__init__.py
pytest_llm_agent/agent.py
pytest_llm_agent/cli.py
pytest_llm_agent/config.py
pytest_llm_agent/repository.py
pytest_llm_agent/tools.py
pytest_llm_agent/core/__init__.py
pytest_llm_agent/core/dtos.py
pytest_llm_agent/core/protocols.py
pytest_llm_agent/core/services.py
pytest_llm_agent-0.1.2.dist-info/licenses/LICENSE
pytest_llm_agent-0.1.2.dist-info/METADATA
pytest_llm_agent-0.1.2.dist-info/WHEEL
pytest_llm_agent-0.1.2.dist-info/entry_points.txt
pytest_llm_agent-0.1.2.dist-info/top_level.txt
pytest_llm_agent-0.1.2.dist-info/RECORD
