Metadata-Version: 2.4
Name: pytest-llm-agent
Version: 0.1.2
Summary: LLM Agent for working with pytest
Project-URL: Homepage, https://github.com/laricko/pytest-llm-agent
Requires-Python: >=3.13
License-File: LICENSE
Requires-Dist: langchain>=1.1.3
Requires-Dist: pytest>=9.0.2
Requires-Dist: typer>=0.20.0
Dynamic: license-file
